sklearn_xarray/__init__.py
sklearn_xarray/data.py
sklearn_xarray/model_selection.py
sklearn_xarray/preprocessing.py
sklearn_xarray/target.py
sklearn_xarray/utils.py
sklearn_xarray/version.py
sklearn_xarray/common/__init__.py
sklearn_xarray/common/base.py
sklearn_xarray/common/wrappers.py
sklearn_xarray/dataarray/__init__.py
sklearn_xarray/dataarray/wrappers.py
sklearn_xarray/dataset/__init__.py
sklearn_xarray/dataset/wrappers.py
sklearn_xarray/externals/__init__.py
sklearn_xarray/externals/_numpy_groupies_np.py
sklearn_xarray/tests/__init__.py
sklearn_xarray/tests/test_common.py
sklearn_xarray/tests/test_data.py
sklearn_xarray/tests/test_dataarray.py
sklearn_xarray/tests/test_dataset.py
sklearn_xarray/tests/test_model_selection.py
sklearn_xarray/tests/test_preprocessing.py
sklearn_xarray/tests/test_target.py
sklearn_xarray/tests/test_utils.py
sklearn_xarray/tests/test_wrapped_estimators.py
sklearn_xarray-0.1.2.dist-info/DESCRIPTION.rst
sklearn_xarray-0.1.2.dist-info/METADATA
sklearn_xarray-0.1.2.dist-info/RECORD
sklearn_xarray-0.1.2.dist-info/WHEEL
sklearn_xarray-0.1.2.dist-info/metadata.json
sklearn_xarray-0.1.2.dist-info/top_level.txt
