Metadata-Version: 2.0
Name: sklearn-xarray
Version: 0.1.2
Summary: xarray integration with sklearn
Home-page: UNKNOWN
Author: Peter Hausamann
Author-email: peter.hausamann@tum.de
License: UNKNOWN
Platform: UNKNOWN
Requires-Dist: scikit-learn (>=0.19)
Requires-Dist: xarray (>=0.10)
Requires-Dist: pandas (>=0.20)
Requires-Dist: cython (>=0.25)
Requires-Dist: numpy (>=1.13)
Requires-Dist: scipy (>=1.0)
